text_unidecode/__init__.py
text_unidecode/data.bin
text_unidecode-1.2.dist-info/DESCRIPTION.rst
text_unidecode-1.2.dist-info/LICENSE.txt
text_unidecode-1.2.dist-info/METADATA
text_unidecode-1.2.dist-info/RECORD
text_unidecode-1.2.dist-info/WHEEL
text_unidecode-1.2.dist-info/metadata.json
text_unidecode-1.2.dist-info/top_level.txt
